Metadata-Version: 2.1
Name: odoo8-addon-account-payment-extension
Version: 8.0.1.0.0.99.dev17
Summary: Migration for account payment extension
Home-page: http://www.antiun.com
Author: Serv. Tecnol. Avanzados - Pedro M. Baeza, Antiun Ingeniería S.L.
Author-email: UNKNOWN
License: UNKNOWN
Platform: UNKNOWN
Classifier: Programming Language :: Python
Classifier: Framework :: Odoo
Requires-Python: ~=2.7
Requires-Dist: odoo (<9.0a,>=8.0a)
